[
  {
    "name": "午餐",
    "category": "餐飲食品",
    "amount": 100,
    "date": "2021-04-20",
    "merchant": "美而美早餐店"
  },
  {
    "name": "魔物獵人:崛起",
    "category": "休閒娛樂",
    "amount": 1920,
    "date": "2021-03-26",
    "merchant": "地下街電玩世界"
  },
  {
    "name": "超速學習",
    "category": "其他",
    "amount": 380,
    "date": "2021-03-13",
    "merchant": "誠品台大店"
  },
  {
    "name": "電話費",
    "category": "家居物業",
    "amount": 713,
    "date": "2021-05-14",
    "merchant": "遠傳電信"
  },
  {
    "name": "停車費",
    "category": "交通出行",
    "amount": 80,
    "date": "2021-04-23",
    "merchant": "公共停車場"
  },
  {
    "name": "健身環大冒險",
    "category": "休閒娛樂",
    "amount": 2550,
    "date": "2021-01-14",
    "merchant": "地下街電玩世界"
  }
]
